{"cameraMode":{"drawMode":0,"name":"Shaded","section":"Shading Mode"},"sceneLighting":true,"audioPlay":false,"sceneViewState":{"m_AlwaysRefresh":false,"showFog":true,"showSkybox":true,"showFlares":true,"showImageEffects":true,"showParticleSystems":true,"showVisualEffectGraphs":true,"m_FxEnabled":true},"in2DMode":false,"pivot":{"x":1.0943626165390015,"y":-0.10202202200889588,"z":-0.05783933028578758},"rotation":{"x":-0.10399266332387924,"y":0.642595112323761,"z":-0.08853500336408615,"w":-0.7539728879928589},"size":25.827285766601564,"orthographic":false}